eksisozluk_scraper.py
eksisozluk_scraper-2.1.1.dist-info/LICENSE
eksisozluk_scraper-2.1.1.dist-info/METADATA
eksisozluk_scraper-2.1.1.dist-info/WHEEL
eksisozluk_scraper-2.1.1.dist-info/entry_points.txt
eksisozluk_scraper-2.1.1.dist-info/top_level.txt
eksisozluk_scraper-2.1.1.dist-info/RECORD
