Metadata-Version: 2.1
Name: eksisozluk-scraper
Version: 2.1.1
Summary: Ekşi Sözlük Scraper - AI-friendly output üreten terminal tabanlı scraper
Home-page: https://github.com/erenseymen/eksisozluk-scraper
Author: Eren Seymen
Author-email: 
License: GPL-3.0-or-later
Project-URL: Homepage, https://github.com/erenseymen/eksisozluk-scraper
Project-URL: Repository, https://github.com/erenseymen/eksisozluk-scraper
Project-URL: Issues, https://github.com/erenseymen/eksisozluk-scraper/issues
Classifier: Development Status :: 4 - Beta
Classifier: Intended Audience :: Developers
Classifier: Programming Language :: Python :: 3
Classifier: Programming Language :: Python :: 3.8
Classifier: Programming Language :: Python :: 3.9
Classifier: Programming Language :: Python :: 3.10
Classifier: Programming Language :: Python :: 3.11
Classifier: Programming Language :: Python :: 3.12
Classifier: Topic :: Internet :: WWW/HTTP :: Browsers
Classifier: Topic :: Software Development :: Libraries :: Python Modules
Requires-Python: >=3.8
License-File: LICENSE
Requires-Dist: argcomplete >=3.0.0
Requires-Dist: beautifulsoup4 >=4.12.0
Requires-Dist: cloudscraper >=1.2.71
Requires-Dist: rich >=13.0.0
Requires-Dist: trafilatura >=1.9.0
Requires-Dist: youtube-transcript-api >=0.6.0
